os_fastapi_middleware/__init__.py
os_fastapi_middleware/config.py
os_fastapi_middleware/exceptions.py
os_fastapi_middleware/utils.py
os_fastapi_middleware/dependencies/__init__.py
os_fastapi_middleware/dependencies/admin_ip_bypass.py
os_fastapi_middleware/dependencies/api_key.py
os_fastapi_middleware/dependencies/ip_whitelist.py
os_fastapi_middleware/dependencies/rate_limit.py
os_fastapi_middleware/middleware/__init__.py
os_fastapi_middleware/middleware/admin_ip_bypass.py
os_fastapi_middleware/middleware/api_key.py
os_fastapi_middleware/middleware/ip_whitelist.py
os_fastapi_middleware/middleware/rate_limit.py
os_fastapi_middleware/middleware/request_logger.py
os_fastapi_middleware/providers/__init__.py
os_fastapi_middleware/providers/base.py
os_fastapi_middleware/providers/memory.py
os_fastapi_middleware/providers/redis.py
os_fastapi_middleware-1.1.10.dist-info/LICENSE.md
os_fastapi_middleware-1.1.10.dist-info/METADATA
os_fastapi_middleware-1.1.10.dist-info/WHEEL
os_fastapi_middleware-1.1.10.dist-info/top_level.txt
os_fastapi_middleware-1.1.10.dist-info/RECORD
