Metadata-Version: 2.1
Name: os-fastapi-middleware
Version: 1.1.10
Summary: Adaptable security middlewares for FastAPI: API keys, rate limiting, IP whitelist
Author-email: Tiago Morais <tcharrua@oddsscanner.com>
License: MIT
Project-URL: Homepage, https://github.com/tcharrua-odds/os-fastapi-middleware
Project-URL: Documentation, https://github.com/tcharrua-odds/os-fastapi-middleware/blob/main/README.md
Project-URL: Repository, https://github.com/tcharrua-odds/os-fastapi-middleware
Project-URL: Issues, https://github.com/tcharrua-odds/os-fastapi-middleware/issues
Keywords: fastapi,middleware,security,rate-limit,api-key,ip-whitelist
Classifier: Development Status :: 4 - Beta
Classifier: Intended Audience :: Developers
Classifier: License :: OSI Approved :: MIT License
Classifier: Programming Language :: Python :: 3
Classifier: Programming Language :: Python :: 3.8
Classifier: Programming Language :: Python :: 3.9
Classifier: Programming Language :: Python :: 3.10
Classifier: Programming Language :: Python :: 3.11
Classifier: Framework :: FastAPI
Requires-Python: >=3.8
License-File: LICENSE.md
Requires-Dist: fastapi >=0.100.0
Requires-Dist: starlette >=0.27.0
Provides-Extra: dev
Requires-Dist: pytest >=7.0.0 ; extra == 'dev'
Requires-Dist: pytest-asyncio >=0.21.0 ; extra == 'dev'
Requires-Dist: pytest-cov >=4.0.0 ; extra == 'dev'
Requires-Dist: httpx >=0.24.0 ; extra == 'dev'
Requires-Dist: black >=23.0.0 ; extra == 'dev'
Requires-Dist: ruff >=0.0.270 ; extra == 'dev'
Provides-Extra: redis
Requires-Dist: redis >=5.0.0 ; extra == 'redis'
